examdays/__init__.py
examdays/function.py
examdays-0.0.16.dist-info/LICENSE
examdays-0.0.16.dist-info/METADATA
examdays-0.0.16.dist-info/WHEEL
examdays-0.0.16.dist-info/entry_points.txt
examdays-0.0.16.dist-info/top_level.txt
examdays-0.0.16.dist-info/RECORD
