Metadata-Version: 2.1
Name: examdays
Version: 0.0.16
Summary: A module that helps you to calculate how many days will you have for preparing your exam.
Home-page: https://github.com/meowmeowmeowcat/exam
Author: meowmeowcat
Author-email: 
License: UNKNOWN
Platform: UNKNOWN
Classifier: Programming Language :: Python :: 3
Classifier: License :: OSI Approved :: MIT License
Classifier: Operating System :: OS Independent
Requires-Python: >=3.6
License-File: LICENSE
Requires-Dist: datetime
